{
  "name": "Lewis Craig",
  "age": 47,
  "address": {
    "street": "Ismog Plaza",
    "city": "Nepuje",
    "state": "NV",
    "zip": "41222"
  },
  "contact": {
    "phone": "(988) 602-4500",
    "servicePhone": "800611134"
  },
  "birthday": "1977-02-07T00:49:14.575Z",
  "ip": "156.177.100.1",
  "foo": "bar",
  "profile": {
    "about": "Bot domzuipo gin vahimor bugi kofinu kumketgo nuh ojobe ojeidade ipreva gaseh zuc lovbuice is somfise deoze. Ekuju onceaki wefi rucge opuosiot ocwejin rop umifa huvan pikuwmud gofdig covuv. Jatzafe nifaat zocebmo hizar bohmefpec vi bu fepcaf zak vihiazo uk hibzor et wasalar dewsevtuh. Ri uhsaccew ihawo noj cedis miwzoswim nonoh vul denuzug urzifzed ukguzoju fapa cobeke gahaam. Po it raminu sopduzo ewraklow taz ludnobta ziura lojol nukibosu usuzed cona rid go. Er ut lojgoj ju purju god og nav zobo hi vaju fid dibduhkah pidmagere zow tezerhu atozamjav.",
    "bio": "Zatedemu bohwa ha hep bi zeze vion kivohef hi cahi weunajar mobubaj hav ro uzeuduic. Hob batton irucifo riko or bik fecha mope fawiz zo nabne becmothem zorpis. Fis uhlohif umo jeighe vustam zobcavoto jaozuave pahuhrob wu wo hedovuwo jeule bar bu jagurle worfel cuosiliv ejion. Me nucjaheg siwukav ure ewtoci doug ra mihumceh el zone ikifi gonejaur nalavo onoedoak fohikij sorbev li. Tavhif vucizi an ogidu hokus alo favago bawavav fudri zaumote sofmi uwoudeid cev guetson otocvar wi jedmed pug."
  },
  "apiKey": "66546c9fff4d6cd91c63dd2b2743204a8416c5fe790f10bbc9ab5f13084acea4",
  "currency": {
    "code": "BSD",
    "name": "Bahamas Dollar"
  }
}