{
  "name": "Philip Sherman",
  "age": 47,
  "address": {
    "street": "Ilpen Point",
    "city": "Fegjelnac",
    "state": "CA",
    "zip": "05871"
  },
  "contact": {
    "phone": "(302) 422-7580",
    "servicePhone": "800275155"
  },
  "birthday": "1969-10-06T08:50:44.540Z",
  "ip": "203.216.185.116",
  "foo": "bar",
  "profile": {
    "about": "Tuzep wilgilzu ezjofok di wizizov daek uso bi vo oskeplik rizomkir vu so. Naosuow ri on zit doeneme zeusefe tespo ori mogum ejiawrin ar weohe unziwmi ofo. Bolep damlimo obadire fop noc sezfi se hahfi wa con uzu mazvugik obiij pit. Uzhik wibazo nawhijev japomaj oga oja fooghab pagva salube feki ru ab iworalnaf serenal ripu vel pioramu ro. Ajizuh beg idle vonget va miafu ir artino coza tuokiog gejgo na jit kupfu za tekowo jobmegof. Coijo wagimu nu govufoc ajserak kuk mu pozot oji osubi wi sakajug.",
    "bio": "Busipcik zal jap igaluneg rohjewzus williwa fejbizof zut pet pav onifab kebvuze ecauwohis juheh ililga jicsevuj uwu el. Af komrolo hesigi ezzu bodtewa mej bapam sinsa pedood se anze jazvum kedutpuv nukzi. Fet rimgoive wenobu iscaj be upjiila sadiw pi da sowza rupzojip fa devamir. Ehni fojjuobe uzewig lekew dezo sirun ja ciduv rehwuh hizvoga opubutlih gi barorfi ved sabuvozi gisagav vojmik. Hi owa vem koeto pe covuip dijup tiasi jiizkoh jawarif ebabofat higah rumci vu navpen."
  },
  "apiKey": "afc94c9024930af20f56e8e383dcc77303467f5b3d8f9f8efb649b06a6ad8058",
  "currency": {
    "code": "MXN",
    "name": "Mexico Peso"
  }
}