{
  "name": "Georgie Meyer",
  "age": 20,
  "address": {
    "street": "Nujud Road",
    "city": "Naonano",
    "state": "WV",
    "zip": "07150"
  },
  "contact": {
    "phone": "(240) 537-8615",
    "servicePhone": "800569712"
  },
  "birthday": "1960-03-02T14:34:06.694Z",
  "ip": "2.35.207.216",
  "foo": "bar",
  "profile": {
    "about": "Akaavuni rumivi epi ilaoholar wasemac bijojbib can rezaazu ke davowi ijgih zatomtuh pizih ofo vithaz fiofdo hu femtatik. Ebvo etego fevij wusizu lim lenzi gali ra mujze revij pis bewewu co wuwpensom refebtu mer keh ledi. Ca tizbuc zovjehisa jekluj kebuzu ze lew om ighu giopu dulri se be.",
    "bio": "Kodcu kaz mam iso binvanek tisugu emewa wifonuet muhgeogo ji hakanta hilogu. Olve we mezaho zad rappam vu ferac nehucho maajani oze foc ca vukoozo. Dod nenum zis jogozwa kom ovwe fes wanazoudo mej luf vagrid ojudir mugsal selgizdar palijuud nipijda jonzu buuzidaz."
  },
  "apiKey": "6f357ad2d75e348e36be1a43af53f4ab46059889d71c9bddc6a729831941d778",
  "currency": {
    "code": "SGD",
    "name": "Singapore Dollar"
  }
}